{"file":"D:\\AIP_lite\\castcoregitintegration\\sourceCode\\Abhyuday--Event-Management-Project-_ef843e1f70362de8888cda6c790f04929042aa1d\\mailerrrrr\\phpmailer\\examples\\scripts\\XRegExp.js","ViolationList":[{"ViolationName":"Avoid Artifacts with High Cyclomatic Complexity","ViolationId":7766,"hrefDoc":"\\Documentation\\7766.json","ViolationsCount":2,"Violations":[{"ID":12,"bookmarks":[{"lineStart":1,"colStart":1,"lineEnd":2,"colEnd":1}]},{"ID":23,"bookmarks":[{"lineStart":340,"colStart":32,"lineEnd":341,"colEnd":1}]}]},{"ViolationName":"Avoid large Artifacts - too many Lines of Code","ViolationId":7842,"hrefDoc":"\\Documentation\\7842.json","ViolationsCount":1,"Violations":[{"ID":33,"bookmarks":[{"lineStart":1,"colStart":1,"lineEnd":2,"colEnd":1}]}]}]}