[{"id":60011,"category":"Transferability","totalViolations":295,"listOfRules":[{"id":2244,"violationName":"Avoid undocumented Web Server pages","violationCount":50},{"id":2254,"violationName":"Avoid large Page files","violationCount":18},{"id":2282,"violationName":"Avoid large Include Files","violationCount":40},{"id":2284,"violationName":"Avoid large JSP Pages - too many Scriptlets","violationCount":10},{"id":7220,"violationName":"Avoid Unused Imports","violationCount":24},{"id":7388,"violationName":"Avoid artifacts having recursive calls","violationCount":8},{"id":7780,"violationName":"Avoid Classes with a very low comment/code ratio","violationCount":8},{"id":7838,"violationName":"Avoid undocumented Methods","violationCount":95},{"id":7842,"violationName":"Avoid large Artifacts - too many Lines of Code","violationCount":33},{"id":7846,"violationName":"Avoid Methods with a very low comment/code ratio","violationCount":8},{"id":1039048,"violationName":"Always prefer set Array designators \"[]\" on the type and not at variable","violationCount":1}]},{"id":60012,"category":"Changeability","totalViolations":288,"listOfRules":[{"id":2242,"violationName":"Avoid direct definition of JavaScript Functions in a Web page","violationCount":4},{"id":2244,"violationName":"Avoid undocumented Web Server pages","violationCount":50},{"id":4566,"violationName":"Avoid declaring Instance Variables without defined access type","violationCount":1},{"id":4568,"violationName":"Avoid declaring Public Instance Variables","violationCount":8},{"id":4576,"violationName":"Provide accessors to Private Fields","violationCount":4},{"id":7220,"violationName":"Avoid Unused Imports","violationCount":24},{"id":7388,"violationName":"Avoid artifacts having recursive calls","violationCount":8},{"id":7780,"violationName":"Avoid Classes with a very low comment/code ratio","violationCount":8},{"id":7794,"violationName":"Avoid Classes with a High Public Data Ratio","violationCount":1},{"id":7838,"violationName":"Avoid undocumented Methods","violationCount":95},{"id":7846,"violationName":"Avoid Methods with a very low comment/code ratio","violationCount":8},{"id":1020312,"violationName":"Avoid use of anonymous functions to attach events","violationCount":76},{"id":1039048,"violationName":"Always prefer set Array designators \"[]\" on the type and not at variable","violationCount":1}]},{"id":60013,"category":"Robustness","totalViolations":348,"listOfRules":[{"id":2232,"violationName":"Pages should use error handling page","violationCount":74},{"id":2242,"violationName":"Avoid direct definition of JavaScript Functions in a Web page","violationCount":4},{"id":2284,"violationName":"Avoid large JSP Pages - too many Scriptlets","violationCount":10},{"id":4656,"violationName":"Avoid declaring throwing an exception and not throwing it","violationCount":1},{"id":4696,"violationName":"Avoid using 'System.err' and 'System.out' within a try catch block","violationCount":7},{"id":4698,"violationName":"Avoid using 'System.err' and 'System.out' outside a try catch block","violationCount":8},{"id":4702,"violationName":"Avoid using 'System.printStackTrace()' outside a try catch block","violationCount":37},{"id":7220,"violationName":"Avoid Unused Imports","violationCount":24},{"id":7388,"violationName":"Avoid artifacts having recursive calls","violationCount":8},{"id":7788,"violationName":"Avoid empty catch blocks","violationCount":26},{"id":7862,"violationName":"Avoid catching an exception of type Exception, RuntimeException, or Throwable","violationCount":54},{"id":8112,"violationName":"Avoid improper processing of the execution status of data handling operations","violationCount":4},{"id":8218,"violationName":"Content type should be checked when receiving a HTTP Post","violationCount":12},{"id":1020312,"violationName":"Avoid use of anonymous functions to attach events","violationCount":76},{"id":1020318,"violationName":"Avoid using jQuery deprecated methods","violationCount":2},{"id":1039048,"violationName":"Always prefer set Array designators \"[]\" on the type and not at variable","violationCount":1}]},{"id":60014,"category":"Performance","totalViolations":264,"listOfRules":[{"id":2242,"violationName":"Avoid direct definition of JavaScript Functions in a Web page","violationCount":4},{"id":7196,"violationName":"Avoid large number of String concatenation","violationCount":15},{"id":7200,"violationName":"Avoid String concatenation in loops","violationCount":4},{"id":7210,"violationName":"Avoid instantiations inside loops","violationCount":3},{"id":7638,"violationName":"Avoid using DriverManager","violationCount":1},{"id":8104,"violationName":"Close database resources ASAP","violationCount":5},{"id":8110,"violationName":"Use dedicated stored procedures when multiple data accesses are needed (ASCPEM-PRF-10)","violationCount":4},{"id":1020020,"violationName":"Avoid blocking page loading with synchronous Javascript import","violationCount":18},{"id":1020308,"violationName":"Always cache the returned objects in variables to be reused","violationCount":208},{"id":1020316,"violationName":"Avoid Universal Selectors","violationCount":2}]},{"id":60015,"category":"SEI Maintainability","totalViolations":0,"listOfRules":[]},{"id":60016,"category":"Security","totalViolations":351,"listOfRules":[{"id":2232,"violationName":"Pages should use error handling page","violationCount":74},{"id":2242,"violationName":"Avoid direct definition of JavaScript Functions in a Web page","violationCount":4},{"id":4566,"violationName":"Avoid declaring Instance Variables without defined access type","violationCount":1},{"id":4656,"violationName":"Avoid declaring throwing an exception and not throwing it","violationCount":1},{"id":4696,"violationName":"Avoid using 'System.err' and 'System.out' within a try catch block","violationCount":7},{"id":4698,"violationName":"Avoid using 'System.err' and 'System.out' outside a try catch block","violationCount":8},{"id":4702,"violationName":"Avoid using 'System.printStackTrace()' outside a try catch block","violationCount":37},{"id":7150,"violationName":"Favor PreparedStatement or CallableStatement over Statement","violationCount":4},{"id":7196,"violationName":"Avoid large number of String concatenation","violationCount":15},{"id":7638,"violationName":"Avoid using DriverManager","violationCount":1},{"id":7788,"violationName":"Avoid empty catch blocks","violationCount":26},{"id":7794,"violationName":"Avoid Classes with a High Public Data Ratio","violationCount":1},{"id":7862,"violationName":"Avoid catching an exception of type Exception, RuntimeException, or Throwable","violationCount":54},{"id":8104,"violationName":"Close database resources ASAP","violationCount":5},{"id":8112,"violationName":"Avoid improper processing of the execution status of data handling operations","violationCount":4},{"id":8218,"violationName":"Content type should be checked when receiving a HTTP Post","violationCount":12},{"id":1020020,"violationName":"Avoid blocking page loading with synchronous Javascript import","violationCount":18},{"id":1020024,"violationName":"Avoid using submit markup related to \"form\" with id attribute","violationCount":42},{"id":1020318,"violationName":"Avoid using jQuery deprecated methods","violationCount":2},{"id":1039008,"violationName":"Avoid thrown Exceptions in servlet methods","violationCount":21},{"id":1039010,"violationName":"Avoid using risky cryptographic hash (JEE)","violationCount":4},{"id":1039016,"violationName":"Avoid Unvalidated URL Redirect","violationCount":10}]},{"id":60017,"category":"Technical Quality Index","totalViolations":961,"listOfRules":[{"id":2232,"violationName":"Pages should use error handling page","violationCount":74},{"id":2242,"violationName":"Avoid direct definition of JavaScript Functions in a Web page","violationCount":4},{"id":2244,"violationName":"Avoid undocumented Web Server pages","violationCount":50},{"id":2254,"violationName":"Avoid large Page files","violationCount":18},{"id":2282,"violationName":"Avoid large Include Files","violationCount":40},{"id":2284,"violationName":"Avoid large JSP Pages - too many Scriptlets","violationCount":10},{"id":4566,"violationName":"Avoid declaring Instance Variables without defined access type","violationCount":1},{"id":4568,"violationName":"Avoid declaring Public Instance Variables","violationCount":8},{"id":4576,"violationName":"Provide accessors to Private Fields","violationCount":4},{"id":4656,"violationName":"Avoid declaring throwing an exception and not throwing it","violationCount":1},{"id":4696,"violationName":"Avoid using 'System.err' and 'System.out' within a try catch block","violationCount":7},{"id":4698,"violationName":"Avoid using 'System.err' and 'System.out' outside a try catch block","violationCount":8},{"id":4702,"violationName":"Avoid using 'System.printStackTrace()' outside a try catch block","violationCount":37},{"id":7150,"violationName":"Favor PreparedStatement or CallableStatement over Statement","violationCount":4},{"id":7196,"violationName":"Avoid large number of String concatenation","violationCount":15},{"id":7200,"violationName":"Avoid String concatenation in loops","violationCount":4},{"id":7210,"violationName":"Avoid instantiations inside loops","violationCount":3},{"id":7220,"violationName":"Avoid Unused Imports","violationCount":24},{"id":7388,"violationName":"Avoid artifacts having recursive calls","violationCount":8},{"id":7638,"violationName":"Avoid using DriverManager","violationCount":1},{"id":7780,"violationName":"Avoid Classes with a very low comment/code ratio","violationCount":8},{"id":7788,"violationName":"Avoid empty catch blocks","violationCount":26},{"id":7794,"violationName":"Avoid Classes with a High Public Data Ratio","violationCount":1},{"id":7838,"violationName":"Avoid undocumented Methods","violationCount":95},{"id":7842,"violationName":"Avoid large Artifacts - too many Lines of Code","violationCount":33},{"id":7846,"violationName":"Avoid Methods with a very low comment/code ratio","violationCount":8},{"id":7862,"violationName":"Avoid catching an exception of type Exception, RuntimeException, or Throwable","violationCount":54},{"id":8104,"violationName":"Close database resources ASAP","violationCount":5},{"id":8110,"violationName":"Use dedicated stored procedures when multiple data accesses are needed (ASCPEM-PRF-10)","violationCount":4},{"id":8112,"violationName":"Avoid improper processing of the execution status of data handling operations","violationCount":4},{"id":8218,"violationName":"Content type should be checked when receiving a HTTP Post","violationCount":12},{"id":1020020,"violationName":"Avoid blocking page loading with synchronous Javascript import","violationCount":18},{"id":1020024,"violationName":"Avoid using submit markup related to \"form\" with id attribute","violationCount":42},{"id":1020308,"violationName":"Always cache the returned objects in variables to be reused","violationCount":208},{"id":1020312,"violationName":"Avoid use of anonymous functions to attach events","violationCount":76},{"id":1020316,"violationName":"Avoid Universal Selectors","violationCount":2},{"id":1020318,"violationName":"Avoid using jQuery deprecated methods","violationCount":2},{"id":1039008,"violationName":"Avoid thrown Exceptions in servlet methods","violationCount":21},{"id":1039010,"violationName":"Avoid using risky cryptographic hash (JEE)","violationCount":4},{"id":1039016,"violationName":"Avoid Unvalidated URL Redirect","violationCount":10},{"id":1039048,"violationName":"Always prefer set Array designators \"[]\" on the type and not at variable","violationCount":1}]},{"id":66031,"category":"Programming Practices","totalViolations":681,"listOfRules":[{"id":2232,"violationName":"Pages should use error handling page","violationCount":74},{"id":2242,"violationName":"Avoid direct definition of JavaScript Functions in a Web page","violationCount":4},{"id":2254,"violationName":"Avoid large Page files","violationCount":18},{"id":2282,"violationName":"Avoid large Include Files","violationCount":40},{"id":2284,"violationName":"Avoid large JSP Pages - too many Scriptlets","violationCount":10},{"id":4566,"violationName":"Avoid declaring Instance Variables without defined access type","violationCount":1},{"id":4568,"violationName":"Avoid declaring Public Instance Variables","violationCount":8},{"id":4576,"violationName":"Provide accessors to Private Fields","violationCount":4},{"id":4656,"violationName":"Avoid declaring throwing an exception and not throwing it","violationCount":1},{"id":4696,"violationName":"Avoid using 'System.err' and 'System.out' within a try catch block","violationCount":7},{"id":4698,"violationName":"Avoid using 'System.err' and 'System.out' outside a try catch block","violationCount":8},{"id":4702,"violationName":"Avoid using 'System.printStackTrace()' outside a try catch block","violationCount":37},{"id":7150,"violationName":"Favor PreparedStatement or CallableStatement over Statement","violationCount":4},{"id":7196,"violationName":"Avoid large number of String concatenation","violationCount":15},{"id":7200,"violationName":"Avoid String concatenation in loops","violationCount":4},{"id":7210,"violationName":"Avoid instantiations inside loops","violationCount":3},{"id":7220,"violationName":"Avoid Unused Imports","violationCount":24},{"id":7388,"violationName":"Avoid artifacts having recursive calls","violationCount":8},{"id":7638,"violationName":"Avoid using DriverManager","violationCount":1},{"id":7788,"violationName":"Avoid empty catch blocks","violationCount":26},{"id":7794,"violationName":"Avoid Classes with a High Public Data Ratio","violationCount":1},{"id":7842,"violationName":"Avoid large Artifacts - too many Lines of Code","violationCount":33},{"id":7862,"violationName":"Avoid catching an exception of type Exception, RuntimeException, or Throwable","violationCount":54},{"id":8104,"violationName":"Close database resources ASAP","violationCount":5},{"id":8110,"violationName":"Use dedicated stored procedures when multiple data accesses are needed (ASCPEM-PRF-10)","violationCount":4},{"id":8112,"violationName":"Avoid improper processing of the execution status of data handling operations","violationCount":4},{"id":1020020,"violationName":"Avoid blocking page loading with synchronous Javascript import","violationCount":18},{"id":1020024,"violationName":"Avoid using submit markup related to \"form\" with id attribute","violationCount":42},{"id":1020308,"violationName":"Always cache the returned objects in variables to be reused","violationCount":208},{"id":1020316,"violationName":"Avoid Universal Selectors","violationCount":2},{"id":1039016,"violationName":"Avoid Unvalidated URL Redirect","violationCount":10},{"id":1039048,"violationName":"Always prefer set Array designators \"[]\" on the type and not at variable","violationCount":1}]},{"id":66032,"category":"Architectural Design","totalViolations":80,"listOfRules":[{"id":2242,"violationName":"Avoid direct definition of JavaScript Functions in a Web page","violationCount":4},{"id":1020312,"violationName":"Avoid use of anonymous functions to attach events","violationCount":76}]},{"id":66033,"category":"Documentation","totalViolations":161,"listOfRules":[{"id":2244,"violationName":"Avoid undocumented Web Server pages","violationCount":50},{"id":7780,"violationName":"Avoid Classes with a very low comment/code ratio","violationCount":8},{"id":7838,"violationName":"Avoid undocumented Methods","violationCount":95},{"id":7846,"violationName":"Avoid Methods with a very low comment/code ratio","violationCount":8}]}]